Metadata-Version: 1.2
Name: lebowski
Version: 1.1.1
Summary: Lebowski lazy importer
Home-page: https://github.com/dme722/lebowski
Author: Drew Ellison
Author-email: dme722@gmail.com
License: UNKNOWN
Project-URL: Bug Reports, https://github.com/dme722/lebowski/issues
Project-URL: Source, https://github.com/dme722/lebowski
Keywords: lazy import
Platform: UNKNOWN
